flask_livetw/__init__.py
flask_livetw/__main__.py
flask_livetw/cmd_build.py
flask_livetw/cmd_dev.py
flask_livetw/cmd_init.py
flask_livetw/config.py
flask_livetw/main.py
flask_livetw/py.typed
flask_livetw/util.py
flask_livetw/resources/global.css
flask_livetw/resources/layout.html
flask_livetw/resources/live_reload.js
flask_livetw/resources/tailwind.config.js
flask_livetw-0.4.4.dist-info/LICENSE
flask_livetw-0.4.4.dist-info/METADATA
flask_livetw-0.4.4.dist-info/WHEEL
flask_livetw-0.4.4.dist-info/entry_points.txt
flask_livetw-0.4.4.dist-info/top_level.txt
flask_livetw-0.4.4.dist-info/RECORD
