Metadata-Version: 2.1
Name: flask-livetw
Version: 0.4.4
Summary: A simple package that enables live reload and Tailwind CSS for Flask templates.
Author-email: Josue <josue.sa.trabajos@gmail.com>
License: MIT License
Project-URL: repository, https://github.com/josu-dev/flask-livetw.git
Project-URL: issues, https://github.com/josu-dev/flask-livetw/issues
Keywords: flask,tailwindcss,livereload,css,html,template
Classifier: Development Status :: 4 - Beta
Classifier: Intended Audience :: Developers
Classifier: Environment :: Console
Classifier: Framework :: Flask
Classifier: Intended Audience :: Developers
Classifier: Natural Language :: English
Classifier: Operating System :: OS Independent
Classifier: Topic :: Software Development :: Libraries :: Python Modules
Classifier: Typing :: Typed
Requires-Python: >=3.8
License-File: LICENSE
Requires-Dist: pytailwindcss >=0.2
Requires-Dist: websockets >=13.1
Requires-Dist: tomli >=2
